smc_kalman/__init__.py
wf_smc_kalman-0.1.0.dist-info/LICENSE
wf_smc_kalman-0.1.0.dist-info/METADATA
wf_smc_kalman-0.1.0.dist-info/WHEEL
wf_smc_kalman-0.1.0.dist-info/top_level.txt
wf_smc_kalman-0.1.0.dist-info/RECORD
